{"__symbolic":"module","version":4,"metadata":{"FabPivotItemComponent":{"__symbolic":"class","extends":{"__symbolic":"reference","module":"@angular-react/core","name":"ReactWrapperComponent","line":44,"character":43},"decorators":[{"__symbolic":"call","expression":{"__symbolic":"reference","module":"@angular/core","name":"Component","line":22,"character":1},"arguments":[{"selector":"fab-pivot-item","exportAs":"fabPivotItem","template":"\n    <PivotItem\n      #reactNode\n      [componentRef]=\"componentRef\"\n      [headerText]=\"headerText\"\n      [headerButtonProps]=\"headerButtonProps\"\n      [itemKey]=\"itemKey\"\n      [ariaLabel]=\"ariaLabel\"\n      [itemCount]=\"itemCount\"\n      [itemIcon]=\"itemIcon\"\n      [keytipProps]=\"keytipProps\"\n      [RenderItemLink]=\"renderItemLink && onRenderItemLink\"\n    >\n      <ReactContent><ng-content></ng-content></ReactContent>\n    </PivotItem>\n  ","styles":["react-renderer"],"changeDetection":{"__symbolic":"select","expression":{"__symbolic":"reference","module":"@angular/core","name":"ChangeDetectionStrategy","line":42,"character":19},"member":"OnPush"}}]}],"members":{"reactNodeRef":[{"__symbolic":"property","decorators":[{"__symbolic":"call","expression":{"__symbolic":"reference","module":"@angular/core","name":"ViewChild","line":45,"character":3},"arguments":["reactNode",{"static":true}]}]}],"disabled":[{"__symbolic":"property","decorators":[{"__symbolic":"call","expression":{"__symbolic":"reference","module":"@angular/core","name":"Input","line":47,"character":3}}]}],"componentRef":[{"__symbolic":"property","decorators":[{"__symbolic":"call","expression":{"__symbolic":"reference","module":"@angular/core","name":"Input","line":48,"character":3}},{"__symbolic":"call","expression":{"__symbolic":"reference","module":"@angular-react/core","name":"passProp","line":48,"character":12}}]}],"headerText":[{"__symbolic":"property","decorators":[{"__symbolic":"call","expression":{"__symbolic":"reference","module":"@angular/core","name":"Input","line":49,"character":3}},{"__symbolic":"call","expression":{"__symbolic":"reference","module":"@angular-react/core","name":"passProp","line":49,"character":12}}]}],"headerButtonProps":[{"__symbolic":"property","decorators":[{"__symbolic":"call","expression":{"__symbolic":"reference","module":"@angular/core","name":"Input","line":50,"character":3}},{"__symbolic":"call","expression":{"__symbolic":"reference","module":"@angular-react/core","name":"passProp","line":50,"character":12}}]}],"itemKey":[{"__symbolic":"property","decorators":[{"__symbolic":"call","expression":{"__symbolic":"reference","module":"@angular/core","name":"Input","line":51,"character":3}},{"__symbolic":"call","expression":{"__symbolic":"reference","module":"@angular-react/core","name":"passProp","line":51,"character":12}}]}],"ariaLabel":[{"__symbolic":"property","decorators":[{"__symbolic":"call","expression":{"__symbolic":"reference","module":"@angular/core","name":"Input","line":52,"character":3}},{"__symbolic":"call","expression":{"__symbolic":"reference","module":"@angular-react/core","name":"passProp","line":52,"character":12}}]}],"itemCount":[{"__symbolic":"property","decorators":[{"__symbolic":"call","expression":{"__symbolic":"reference","module":"@angular/core","name":"Input","line":53,"character":3}},{"__symbolic":"call","expression":{"__symbolic":"reference","module":"@angular-react/core","name":"passProp","line":53,"character":12}}]}],"itemIcon":[{"__symbolic":"property","decorators":[{"__symbolic":"call","expression":{"__symbolic":"reference","module":"@angular/core","name":"Input","line":54,"character":3}},{"__symbolic":"call","expression":{"__symbolic":"reference","module":"@angular-react/core","name":"passProp","line":54,"character":12}}]}],"keytipProps":[{"__symbolic":"property","decorators":[{"__symbolic":"call","expression":{"__symbolic":"reference","module":"@angular/core","name":"Input","line":55,"character":3}},{"__symbolic":"call","expression":{"__symbolic":"reference","module":"@angular-react/core","name":"passProp","line":55,"character":12}}]}],"renderItemLink":[{"__symbolic":"property","decorators":[{"__symbolic":"call","expression":{"__symbolic":"reference","module":"@angular/core","name":"Input","line":56,"character":3}},{"__symbolic":"call","expression":{"__symbolic":"reference","module":"@angular-react/core","name":"passProp","line":56,"character":12}}]}],"onRenderItemLink":[{"__symbolic":"property","decorators":[{"__symbolic":"call","expression":{"__symbolic":"reference","module":"@angular-react/core","name":"passProp","line":58,"character":3}}]}],"__ctor__":[{"__symbolic":"constructor","parameters":[{"__symbolic":"reference","module":"@angular/core","name":"ElementRef","line":60,"character":26},{"__symbolic":"reference","module":"@angular/core","name":"ChangeDetectorRef","line":60,"character":57},{"__symbolic":"reference","module":"@angular/core","name":"Renderer2","line":60,"character":86},{"__symbolic":"reference","module":"@angular/core","name":"NgZone","line":60,"character":105}]}],"ngOnInit":[{"__symbolic":"method"}]}},"FabPivotComponent":{"__symbolic":"class","extends":{"__symbolic":"reference","module":"@angular-react/core","name":"ReactWrapperComponent","line":97,"character":39},"decorators":[{"__symbolic":"call","expression":{"__symbolic":"reference","module":"@angular/core","name":"Component","line":69,"character":1},"arguments":[{"selector":"fab-pivot","exportAs":"fabPivot","template":"\n    <Disguise\n      #reactNode\n      [disguiseRootAs]=\"PivotType\"\n      [disguiseChildrenAs]=\"PivotItemType\"\n      [ngChildComponents]=\"children || pivotItems?.toArray()\"\n      [componentRef]=\"componentRef\"\n      [styles]=\"styles\"\n      [theme]=\"theme\"\n      [className]=\"className\"\n      [defaultSelectedKey]=\"defaultSelectedKey\"\n      [defaultSelectedIndex]=\"defaultSelectedIndex\"\n      [selectedKey]=\"selectedKey\"\n      [linkSize]=\"linkSize\"\n      [linkFormat]=\"linkFormat\"\n      [headersOnly]=\"headersOnly\"\n      [getTabId]=\"getTabId\"\n      [LinkClick]=\"onLinkClickHandler\"\n    >\n      <ReactContent><ng-content select=\"fab-pivot-item\"></ng-content></ReactContent>\n    </Disguise>\n  ","styles":["react-renderer"],"changeDetection":{"__symbolic":"select","expression":{"__symbolic":"reference","module":"@angular/core","name":"ChangeDetectionStrategy","line":95,"character":19},"member":"OnPush"}}]}],"members":{"reactNodeRef":[{"__symbolic":"property","decorators":[{"__symbolic":"call","expression":{"__symbolic":"reference","module":"@angular/core","name":"ViewChild","line":101,"character":3},"arguments":["reactNode",{"static":true}]}]}],"pivotItems":[{"__symbolic":"property","decorators":[{"__symbolic":"call","expression":{"__symbolic":"reference","module":"@angular/core","name":"ContentChildren","line":103,"character":3},"arguments":[{"__symbolic":"reference","name":"FabPivotItemComponent"}]}]}],"componentRef":[{"__symbolic":"property","decorators":[{"__symbolic":"call","expression":{"__symbolic":"reference","module":"@angular/core","name":"Input","line":105,"character":3}}]}],"styles":[{"__symbolic":"property","decorators":[{"__symbolic":"call","expression":{"__symbolic":"reference","module":"@angular/core","name":"Input","line":106,"character":3}}]}],"theme":[{"__symbolic":"property","decorators":[{"__symbolic":"call","expression":{"__symbolic":"reference","module":"@angular/core","name":"Input","line":107,"character":3}}]}],"className":[{"__symbolic":"property","decorators":[{"__symbolic":"call","expression":{"__symbolic":"reference","module":"@angular/core","name":"Input","line":108,"character":3}}]}],"defaultSelectedKey":[{"__symbolic":"property","decorators":[{"__symbolic":"call","expression":{"__symbolic":"reference","module":"@angular/core","name":"Input","line":109,"character":3}}]}],"defaultSelectedIndex":[{"__symbolic":"property","decorators":[{"__symbolic":"call","expression":{"__symbolic":"reference","module":"@angular/core","name":"Input","line":110,"character":3}}]}],"selectedKey":[{"__symbolic":"property","decorators":[{"__symbolic":"call","expression":{"__symbolic":"reference","module":"@angular/core","name":"Input","line":111,"character":3}}]}],"linkSize":[{"__symbolic":"property","decorators":[{"__symbolic":"call","expression":{"__symbolic":"reference","module":"@angular/core","name":"Input","line":112,"character":3}}]}],"linkFormat":[{"__symbolic":"property","decorators":[{"__symbolic":"call","expression":{"__symbolic":"reference","module":"@angular/core","name":"Input","line":113,"character":3}}]}],"headersOnly":[{"__symbolic":"property","decorators":[{"__symbolic":"call","expression":{"__symbolic":"reference","module":"@angular/core","name":"Input","line":114,"character":3}}]}],"getTabId":[{"__symbolic":"property","decorators":[{"__symbolic":"call","expression":{"__symbolic":"reference","module":"@angular/core","name":"Input","line":115,"character":3}}]}],"children":[{"__symbolic":"property","decorators":[{"__symbolic":"call","expression":{"__symbolic":"reference","module":"@angular/core","name":"Input","line":116,"character":3}}]}],"onLinkClick":[{"__symbolic":"property","decorators":[{"__symbolic":"call","expression":{"__symbolic":"reference","module":"@angular/core","name":"Output","line":118,"character":3}}]}],"__ctor__":[{"__symbolic":"constructor","parameters":[{"__symbolic":"reference","module":"@angular/core","name":"ElementRef","line":60,"character":26},{"__symbolic":"reference","module":"@angular/core","name":"ChangeDetectorRef","line":60,"character":57},{"__symbolic":"reference","module":"@angular/core","name":"Renderer2","line":60,"character":86}]}],"onLinkClickHandler":[{"__symbolic":"method"}]}},"FabPivotModule":{"__symbolic":"class","decorators":[{"__symbolic":"call","expression":{"__symbolic":"reference","module":"@angular/core","name":"NgModule","line":11,"character":1},"arguments":[{"imports":[{"__symbolic":"reference","module":"@angular/common","name":"CommonModule","line":12,"character":12}],"declarations":[{"__symbolic":"reference","name":"FabPivotComponent"},{"__symbolic":"reference","name":"FabPivotItemComponent"}],"exports":[{"__symbolic":"reference","name":"FabPivotComponent"},{"__symbolic":"reference","name":"FabPivotItemComponent"}],"schemas":[{"__symbolic":"reference","module":"@angular/core","name":"NO_ERRORS_SCHEMA","line":15,"character":12}]}]}],"members":{"__ctor__":[{"__symbolic":"constructor"}]}}},"origins":{"FabPivotItemComponent":"./pivot.component","FabPivotComponent":"./pivot.component","FabPivotModule":"./pivot.module"},"importAs":"@angular-react/fabric/lib/components/pivot"}